[
    {
      "Version": 1,
      "Key": "213225",
      "Type": "City",
      "Rank": 30,
      "LocalizedName": "Jerusalem",
      "Country": {
        "ID": "IL",
        "LocalizedName": "Israel"
      },
      "AdministrativeArea": {
        "ID": "JM",
        "LocalizedName": "Jerusalem"
      }
    },
    {
      "Version": 1,
      "Key": "250835",
      "Type": "City",
      "Rank": 65,
      "LocalizedName": "Jerusalem",
      "Country": {
        "ID": "NZ",
        "LocalizedName": "New Zealand"
      },
      "AdministrativeArea": {
        "ID": "MWT",
        "LocalizedName": "Manawatu-Wanganui"
      }
    },
    {
      "Version": 1,
      "Key": "128752",
      "Type": "City",
      "Rank": 65,
      "LocalizedName": "Jerusalen",
      "Country": {
        "ID": "SV",
        "LocalizedName": "El Salvador"
      },
      "AdministrativeArea": {
        "ID": "PA",
        "LocalizedName": "La Paz"
      }
    },
    {
      "Version": 1,
      "Key": "32864",
      "Type": "City",
      "Rank": 75,
      "LocalizedName": "Jerusalen",
      "Country": {
        "ID": "BO",
        "LocalizedName": "Bolivia"
      },
      "AdministrativeArea": {
        "ID": "B",
        "LocalizedName": "El Beni"
      }
    },
    {
      "Version": 1,
      "Key": "221483",
      "Type": "City",
      "Rank": 75,
      "LocalizedName": "Jerusalem",
      "Country": {
        "ID": "JM",
        "LocalizedName": "Jamaica"
      },
      "AdministrativeArea": {
        "ID": "10",
        "LocalizedName": "Westmoreland"
      }
    },
    {
      "Version": 1,
      "Key": "1376675",
      "Type": "City",
      "Rank": 85,
      "LocalizedName": "Jerusalem",
      "Country": {
        "ID": "CZ",
        "LocalizedName": "Czechia"
      },
      "AdministrativeArea": {
        "ID": "20",
        "LocalizedName": "Central Bohemian"
      }
    },
    {
      "Version": 1,
      "Key": "1062990",
      "Type": "City",
      "Rank": 85,
      "LocalizedName": "Jerusalem",
      "Country": {
        "ID": "MX",
        "LocalizedName": "Mexico"
      },
      "AdministrativeArea": {
        "ID": "CHP",
        "LocalizedName": "Chiapas"
      }
    },
    {
      "Version": 1,
      "Key": "1062987",
      "Type": "City",
      "Rank": 85,
      "LocalizedName": "Jerusalem",
      "Country": {
        "ID": "MX",
        "LocalizedName": "Mexico"
      },
      "AdministrativeArea": {
        "ID": "DUR",
        "LocalizedName": "Durango"
      }
    },
    {
      "Version": 1,
      "Key": "1062988",
      "Type": "City",
      "Rank": 85,
      "LocalizedName": "Jerusalem",
      "Country": {
        "ID": "MX",
        "LocalizedName": "Mexico"
      },
      "AdministrativeArea": {
        "ID": "JAL",
        "LocalizedName": "Jalisco"
      }
    },
    {
      "Version": 1,
      "Key": "2115414",
      "Type": "City",
      "Rank": 85,
      "LocalizedName": "Jerusalem",
      "Country": {
        "ID": "US",
        "LocalizedName": "United States"
      },
      "AdministrativeArea": {
        "ID": "OH",
        "LocalizedName": "Ohio"
      }
    },
    {
      "Version": 1,
      "Key": "213490",
      "Type": "City",
      "Rank": 20,
      "LocalizedName": "Rome",
      "Country": {
        "ID": "IT",
        "LocalizedName": "Italy"
      },
      "AdministrativeArea": {
        "ID": "62",
        "LocalizedName": "Lazio"
      }
    },
    {
      "Version": 1,
      "Key": "295146",
      "Type": "City",
      "Rank": 21,
      "LocalizedName": "Rostov-on-Don",
      "Country": {
        "ID": "RU",
        "LocalizedName": "Russia"
      },
      "AdministrativeArea": {
        "ID": "ROS",
        "LocalizedName": "Rostov"
      }
    },
    {
      "Version": 1,
      "Key": "11222",
      "Type": "City",
      "Rank": 25,
      "LocalizedName": "Rosario",
      "Country": {
        "ID": "AR",
        "LocalizedName": "Argentina"
      },
      "AdministrativeArea": {
        "ID": "S",
        "LocalizedName": "Santa Fe"
      }
    },
    {
      "Version": 1,
      "Key": "251688",
      "Type": "City",
      "Rank": 32,
      "LocalizedName": "Rotterdam",
      "Country": {
        "ID": "NL",
        "LocalizedName": "Netherlands"
      },
      "AdministrativeArea": {
        "ID": "ZH",
        "LocalizedName": "South Holland"
      }
    },
    {
      "Version": 1,
      "Key": "58423",
      "Type": "City",
      "Rank": 33,
      "LocalizedName": "Rongshui County",
      "Country": {
        "ID": "CN",
        "LocalizedName": "China"
      },
      "AdministrativeArea": {
        "ID": "GX",
        "LocalizedName": "Guangxi"
      }
    },
    {
      "Version": 1,
      "Key": "58757",
      "Type": "City",
      "Rank": 33,
      "LocalizedName": "Rongcheng County",
      "Country": {
        "ID": "CN",
        "LocalizedName": "China"
      },
      "AdministrativeArea": {
        "ID": "HE",
        "LocalizedName": "Hebei"
      }
    },
    {
      "Version": 1,
      "Key": "2332700",
      "Type": "City",
      "Rank": 35,
      "LocalizedName": "Rong County",
      "Country": {
        "ID": "CN",
        "LocalizedName": "China"
      },
      "AdministrativeArea": {
        "ID": "GX",
        "LocalizedName": "Guangxi"
      }
    },
    {
      "Version": 1,
      "Key": "2333484",
      "Type": "City",
      "Rank": 35,
      "LocalizedName": "Rong County",
      "Country": {
        "ID": "CN",
        "LocalizedName": "China"
      },
      "AdministrativeArea": {
        "ID": "SC",
        "LocalizedName": "Sichuan"
      }
    },
    {
      "Version": 1,
      "Key": "188421",
      "Type": "City",
      "Rank": 35,
      "LocalizedName": "Rohtak",
      "Country": {
        "ID": "IN",
        "LocalizedName": "India"
      },
      "AdministrativeArea": {
        "ID": "HR",
        "LocalizedName": "Haryana"
      }
    },
    {
      "Version": 1,
      "Key": "265787",
      "Type": "City",
      "Rank": 35,
      "LocalizedName": "Rodriguez",
      "Country": {
        "ID": "PH",
        "LocalizedName": "Philippines"
      },
      "AdministrativeArea": {
        "ID": "RIZ",
        "LocalizedName": "Rizal"
      }
    },
    {
      "Version": 1,
      "Key": "210841",
      "Type": "City",
      "Rank": 20,
      "LocalizedName": "Tehran",
      "Country": {
        "ID": "IR",
        "LocalizedName": "Iran"
      },
      "AdministrativeArea": {
        "ID": "07",
        "LocalizedName": "Tehran"
      }
    },
    {
      "Version": 1,
      "Key": "60592",
      "Type": "City",
      "Rank": 23,
      "LocalizedName": "Tengzhou",
      "Country": {
        "ID": "CN",
        "LocalizedName": "China"
      },
      "AdministrativeArea": {
        "ID": "SD",
        "LocalizedName": "Shandong"
      }
    },
    {
      "Version": 1,
      "Key": "188046",
      "Type": "City",
      "Rank": 30,
      "LocalizedName": "Tegucigalpa",
      "Country": {
        "ID": "HN",
        "LocalizedName": "Honduras"
      },
      "AdministrativeArea": {
        "ID": "FM",
        "LocalizedName": "Francisco Morazán"
      }
    },
    {
      "Version": 1,
      "Key": "45253",
      "Type": "City",
      "Rank": 31,
      "LocalizedName": "Teresina",
      "Country": {
        "ID": "BR",
        "LocalizedName": "Brazil"
      },
      "AdministrativeArea": {
        "ID": "PI",
        "LocalizedName": "Piauí"
      }
    },
    {
      "Version": 1,
      "Key": "215854",
      "Type": "City",
      "Rank": 31,
      "LocalizedName": "Tel Aviv",
      "Country": {
        "ID": "IL",
        "LocalizedName": "Israel"
      },
      "AdministrativeArea": {
        "ID": "TA",
        "LocalizedName": "Tel Aviv"
      }
    },
    {
      "Version": 1,
      "Key": "234337",
      "Type": "City",
      "Rank": 31,
      "LocalizedName": "Tepic",
      "Country": {
        "ID": "MX",
        "LocalizedName": "Mexico"
      },
      "AdministrativeArea": {
        "ID": "NAY",
        "LocalizedName": "Nayarit"
      }
    },
    {
      "Version": 1,
      "Key": "246100",
      "Type": "City",
      "Rank": 32,
      "LocalizedName": "Tetouan",
      "Country": {
        "ID": "MA",
        "LocalizedName": "Morocco"
      },
      "AdministrativeArea": {
        "ID": "01",
        "LocalizedName": "Tanger-Tétouan-Al Hoceïma"
      }
    },
    {
      "Version": 1,
      "Key": "61484",
      "Type": "City",
      "Rank": 33,
      "LocalizedName": "Tengchong",
      "Country": {
        "ID": "CN",
        "LocalizedName": "China"
      },
      "AdministrativeArea": {
        "ID": "YN",
        "LocalizedName": "Yunnan"
      }
    },
    {
      "Version": 1,
      "Key": "3558994",
      "Type": "City",
      "Rank": 35,
      "LocalizedName": "Tecámac",
      "Country": {
        "ID": "MX",
        "LocalizedName": "Mexico"
      },
      "AdministrativeArea": {
        "ID": "MEX",
        "LocalizedName": "México"
      }
    },
    {
      "Version": 1,
      "Key": "234828",
      "Type": "City",
      "Rank": 35,
      "LocalizedName": "Tehuacán",
      "Country": {
        "ID": "MX",
        "LocalizedName": "Mexico"
      },
      "AdministrativeArea": {
        "ID": "PUE",
        "LocalizedName": "Puebla"
      }
    },
    {
      "Version": 1,
      "Key": "2333525",
      "Type": "City",
      "Rank": 13,
      "LocalizedName": "New Territories",
      "Country": {
        "ID": "HK",
        "LocalizedName": "Hong Kong"
      },
      "AdministrativeArea": {
        "ID": "TW",
        "LocalizedName": "Tsuen Wan"
      }
    },
    {
      "Version": 1,
      "Key": "349727",
      "Type": "City",
      "Rank": 15,
      "LocalizedName": "New York",
      "Country": {
        "ID": "US",
        "LocalizedName": "United States"
      },
      "AdministrativeArea": {
        "ID": "NY",
        "LocalizedName": "New York"
      }
    },
    {
      "Version": 1,
      "Key": "2515397",
      "Type": "City",
      "Rank": 21,
      "LocalizedName": "New Taipei City",
      "Country": {
        "ID": "TW",
        "LocalizedName": "Taiwan"
      },
      "AdministrativeArea": {
        "ID": "NWT",
        "LocalizedName": "New Taipei City"
      }
    },
    {
      "Version": 1,
      "Key": "187745",
      "Type": "City",
      "Rank": 30,
      "LocalizedName": "New Delhi",
      "Country": {
        "ID": "IN",
        "LocalizedName": "India"
      },
      "AdministrativeArea": {
        "ID": "DL",
        "LocalizedName": "Delhi"
      }
    },
    {
      "Version": 1,
      "Key": "298885",
      "Type": "City",
      "Rank": 32,
      "LocalizedName": "Newcastle",
      "Country": {
        "ID": "ZA",
        "LocalizedName": "South Africa"
      },
      "AdministrativeArea": {
        "ID": "NL",
        "LocalizedName": "Kwazulu-Natal"
      }
    },
    {
      "Version": 1,
      "Key": "12777",
      "Type": "City",
      "Rank": 35,
      "LocalizedName": "Newcastle",
      "Country": {
        "ID": "AU",
        "LocalizedName": "Australia"
      },
      "AdministrativeArea": {
        "ID": "NSW",
        "LocalizedName": "New South Wales"
      }
    },
    {
      "Version": 1,
      "Key": "348585",
      "Type": "City",
      "Rank": 35,
      "LocalizedName": "New Orleans",
      "Country": {
        "ID": "US",
        "LocalizedName": "United States"
      },
      "AdministrativeArea": {
        "ID": "LA",
        "LocalizedName": "Louisiana"
      }
    },
    {
      "Version": 1,
      "Key": "349530",
      "Type": "City",
      "Rank": 35,
      "LocalizedName": "Newark",
      "Country": {
        "ID": "US",
        "LocalizedName": "United States"
      },
      "AdministrativeArea": {
        "ID": "NJ",
        "LocalizedName": "New Jersey"
      }
    },
    {
      "Version": 1,
      "Key": "329683",
      "Type": "City",
      "Rank": 41,
      "LocalizedName": "Newcastle upon Tyne",
      "Country": {
        "ID": "GB",
        "LocalizedName": "United Kingdom"
      },
      "AdministrativeArea": {
        "ID": "NET",
        "LocalizedName": "Newcastle upon Tyne"
      }
    },
    {
      "Version": 1,
      "Key": "2530492",
      "Type": "City",
      "Rank": 41,
      "LocalizedName": "Newport",
      "Country": {
        "ID": "GB",
        "LocalizedName": "United Kingdom"
      },
      "AdministrativeArea": {
        "ID": "NWP",
        "LocalizedName": "Newport"
      }
    }
  ]